Metadata-Version: 2.1
Name: vinclab-distri
Version: 0.1
Summary: Gaussian and Binomail distributions
Author-email: contact@vincentsalas.fr
